mc/__init__.py
mc/math_commands.py
mcp_cli/__init__.py
mcp_cli/server_command.py
monxcli/__init__.py
monxcli/command_parser.py
monxcli/commands.py
monxcli/mcp_bridge.py
monxcli-1.0.1.dist-info/licenses/LICENSE
pm/__init__.py
pm/pmtool.py
monxcli-1.0.1.dist-info/METADATA
monxcli-1.0.1.dist-info/WHEEL
monxcli-1.0.1.dist-info/entry_points.txt
monxcli-1.0.1.dist-info/top_level.txt
monxcli-1.0.1.dist-info/RECORD
