Metadata-Version: 2.4
Name: monxcli
Version: 1.0.1
Summary: A simple, extensible git like CLI framework.
Home-page: https://gitlab.com/mongkoy/monxcli.git
Author: Reihmon Estremos
Author-email: koydaut@gmail.com
License: MIT
Classifier: Programming Language :: Python :: 3
Classifier: License :: OSI Approved :: MIT License
Classifier: Operating System :: OS Independent
Requires-Python: >=3.7
License-File: LICENSE
Dynamic: author
Dynamic: author-email
Dynamic: classifier
Dynamic: description
Dynamic: description-content-type
Dynamic: home-page
Dynamic: license
Dynamic: license-file
Dynamic: requires-python
Dynamic: summary
